markdown_callouts/__init__.py
markdown_callouts-0.2.0.dist-info/entry_points.txt
markdown_callouts-0.2.0.dist-info/LICENSE.md
markdown_callouts-0.2.0.dist-info/WHEEL
markdown_callouts-0.2.0.dist-info/METADATA
markdown_callouts-0.2.0.dist-info/RECORD
