Metadata-Version: 2.1
Name: markdown-callouts
Version: 0.2.0
Summary: Markdown extension: a classier syntax for admonitions
Home-page: https://github.com/oprypin/markdown-callouts
License: MIT
Keywords: markdown,extensions
Author: Oleh Prypin
Author-email: oleh@pryp.in
Requires-Python: >=3.6,<4.0
Classifier: License :: OSI Approved :: MIT License
Classifier: Programming Language :: Python :: 3
Classifier: Programming Language :: Python :: 3.6
Classifier: Programming Language :: Python :: 3.7
Classifier: Programming Language :: Python :: 3.8
Classifier: Programming Language :: Python :: 3.9
Requires-Dist: Markdown (>=3.3,<4.0)
Project-URL: Repository, https://github.com/oprypin/markdown-callouts
